{
  "connections": [
    {
      "_id": "619459086b56da1078d3cf62",
      "index": 0,
      "label": "pariatur",
      "guid": "83934cd6-fb44-458d-a3d5-21cd3022941a",
      "isActive": false,
      "picture": "http://placehold.it/32x32",
      "level": 35,
      "about": "Enim ad esse nostrud voluptate ex nisi ea ad ut deserunt. Ea aute non esse fugiat ipsum irure cillum mollit exercitation eiusmod incididunt ipsum. Eu id exercitation magna quis consectetur. Pariatur elit officia consequat labore aute enim est nisi aute et cupidatat Lorem minim aliqua. Incididunt fugiat adipisicing ipsum eu enim sint deserunt nulla nulla deserunt id.\r\n",
      "registered": "2017-07-18T12:44:24 +03:00",
      "latitude": -31.680412,
      "longitude": 168.271024,
      "connections": [
        {
          "_id": "6194590809beac7af1db9197",
          "index": 0,
          "label": "velit",
          "guid": "ebdab89c-ce77-49ab-9aba-f5c99227a79a",
          "isActive": true,
          "picture": "http://placehold.it/32x32",
          "level": 21,
          "about": "Magna Lorem duis in amet commodo commodo. Cillum irure irure mollit exercitation esse culpa aliqua ut. Minim nulla velit tempor cillum incididunt ex labore cillum id. Quis anim officia reprehenderit amet labore eiusmod aute nulla do ullamco.\r\n",
          "registered": "2020-11-23T02:14:30 +03:00",
          "latitude": -66.265565,
          "longitude": 24.357013,
          "tags": [
            "qui",
            "qui",
            "fugiat",
            "adipisicing",
            "non",
            "incididunt",
            "minim"
          ]
        },
        {
          "_id": "61945908daa72c63c52f5917",
          "index": 1,
          "label": "nisi",
          "guid": "7323402d-27ca-42cb-a65a-144ddbbbe338",
          "isActive": true,
          "picture": "http://placehold.it/32x32",
          "level": 38,
          "about": "Elit officia sunt veniam sit consequat nisi eiusmod eiusmod eu et ad voluptate occaecat. Sit Lorem sit Lorem deserunt ex elit labore. Exercitation commodo anim consectetur officia mollit exercitation aliqua quis magna aute esse. Sunt culpa ex ut cupidatat adipisicing consectetur nulla incididunt deserunt tempor quis tempor minim. Do dolore irure esse commodo proident dolor sunt mollit magna laborum ullamco. In est mollit sint anim irure id anim ea non culpa sit.\r\n",
          "registered": "2015-11-19T06:04:05 +02:00",
          "latitude": 58.153482,
          "longitude": 49.213363,
          "tags": [
            "ex",
            "dolore",
            "non",
            "incididunt",
            "deserunt",
            "fugiat",
            "pariatur"
          ]
        },
        {
          "_id": "619459081b9359627ffb174d",
          "index": 2,
          "label": "voluptate",
          "guid": "87470d4d-f066-41ea-94f1-70a215ac398b",
          "isActive": true,
          "picture": "http://placehold.it/32x32",
          "level": 31,
          "about": "Adipisicing aliqua excepteur labore magna tempor culpa mollit tempor. Sunt aliqua deserunt cupidatat consequat ullamco occaecat laborum dolore consequat ullamco aliquip elit. Proident pariatur cillum commodo dolor exercitation esse laboris fugiat mollit. Id dolor et sint dolore ad laboris commodo nostrud in magna ullamco sit adipisicing. Pariatur enim id tempor incididunt. Anim qui pariatur adipisicing magna amet id anim proident consectetur deserunt dolor ea qui.\r\n",
          "registered": "2015-09-04T11:47:43 +03:00",
          "latitude": 61.356344,
          "longitude": 127.848301,
          "tags": [
            "minim",
            "do",
            "nostrud",
            "id",
            "Lorem",
            "ullamco",
            "ad"
          ]
        }
      ],
      "tags": [
        "ullamco",
        "sunt",
        "in",
        "commodo",
        "laboris",
        "ipsum",
        "in"
      ]
    },
    {
      "_id": "6194590847e29864f074fd6b",
      "index": 1,
      "label": "minim",
      "guid": "a9985a30-bf91-4d72-b387-4b58ea8851ab",
      "isActive": true,
      "picture": "http://placehold.it/32x32",
      "level": 28,
      "about": "Commodo sint consequat irure pariatur pariatur tempor ipsum nostrud reprehenderit ipsum et aliqua officia duis. Officia in minim anim nisi voluptate ex nulla do anim. Consequat excepteur eiusmod sit mollit. Commodo deserunt do aute et duis do dolor in incididunt commodo ad. Est commodo dolor laborum adipisicing eiusmod.\r\n",
      "registered": "2019-10-10T05:50:01 +03:00",
      "latitude": 14.312911,
      "longitude": 149.959241,
      "connections": [
        {
          "_id": "61945908061bb8557d39c99f",
          "index": 0,
          "label": "aliqua",
          "guid": "93fb4567-5269-47d3-9b41-eadc85c36fbb",
          "isActive": true,
          "picture": "http://placehold.it/32x32",
          "level": 24,
          "about": "Sint eu tempor esse in id est sunt proident. Id esse laborum tempor magna labore cillum ipsum. Ipsum laborum in aliquip laboris ad excepteur pariatur consectetur cupidatat voluptate minim aliqua fugiat in. Magna irure culpa cupidatat labore occaecat incididunt officia do aute. Nulla mollit pariatur sint adipisicing commodo magna. Pariatur anim ad culpa consequat sunt velit officia quis.\r\n",
          "registered": "2018-10-05T10:33:51 +03:00",
          "latitude": 2.143963,
          "longitude": 72.330458,
          "tags": [
            "do",
            "mollit",
            "dolor",
            "laborum",
            "nisi",
            "culpa",
            "consectetur"
          ]
        },
        {
          "_id": "61945908e0a0b705972e12e6",
          "index": 1,
          "label": "ipsum",
          "guid": "f553a6f2-eb47-4afb-96e5-f51fef75812e",
          "isActive": true,
          "picture": "http://placehold.it/32x32",
          "level": 36,
          "about": "Nulla adipisicing elit aliquip veniam aliqua commodo deserunt ad commodo ex aliquip. Elit qui quis deserunt incididunt labore exercitation nostrud. Duis voluptate velit esse adipisicing ut ullamco sunt.\r\n",
          "registered": "2017-01-13T06:07:33 +02:00",
          "latitude": 9.398832,
          "longitude": -11.03003,
          "tags": [
            "officia",
            "nostrud",
            "do",
            "minim",
            "ut",
            "occaecat",
            "et"
          ]
        }
      ],
      "tags": [
        "id",
        "ex",
        "cupidatat",
        "ea",
        "minim",
        "nostrud",
        "adipisicing"
      ],
      "folders": [
        {
          "id": 0,
          "name": "reprehenderit",
          "label": "folder-label",
          "highlight": "brown",
          "files": [
            {
              "id": 0,
              "name": "id",
              "label": "file-label",
              "balance": "$2,958.52",
              "highlight": "brown",
              "connection": {
                "_id": "6194590890812bf4100f4e9f",
                "index": 0,
                "label": "quis",
                "guid": "336b7f6e-b131-4ece-9ae8-6f2141b9b4b3",
                "isActive": true,
                "balance": "$1,838.07",
                "picture": "http://placehold.it/32x32",
                "level": 38,
                "highlight": "blue",
                "about": "Reprehenderit qui dolor nulla tempor culpa est pariatur id. Occaecat deserunt veniam nostrud commodo cupidatat in. Qui cupidatat commodo et est culpa fugiat. Fugiat tempor esse officia velit elit do consectetur quis ex.\r\n",
                "registered": "2015-04-05T01:17:40 +03:00",
                "latitude": 54.623494,
                "longitude": -158.714092,
                "tags": [
                  "amet",
                  "eu",
                  "Lorem",
                  "sit",
                  "labore",
                  "officia",
                  "pariatur"
                ]
              }
            },
            {
              "id": 1,
              "name": "occaecat",
              "label": "file-label",
              "balance": "$1,036.28",
              "highlight": "yellow",
              "connection": {
                "_id": "619459082921931df2a2d700",
                "index": 1,
                "label": "in",
                "guid": "001ed7d5-d3f3-4642-b659-01d1523a1084",
                "isActive": false,
                "balance": "$1,143.21",
                "picture": "http://placehold.it/32x32",
                "level": 20,
                "highlight": "red",
                "about": "Velit excepteur sint cillum velit labore voluptate consequat aute laborum aute amet ex amet amet. Non et eiusmod dolor nostrud reprehenderit dolor minim minim sunt excepteur incididunt. Irure culpa duis velit reprehenderit laborum cillum. Culpa anim qui ipsum veniam cillum minim.\r\n",
                "registered": "2014-05-16T06:56:55 +03:00",
                "latitude": -73.172477,
                "longitude": 113.931981,
                "tags": [
                  "dolor",
                  "sunt",
                  "Lorem",
                  "in",
                  "proident",
                  "sint",
                  "magna"
                ]
              }
            },
            {
              "id": 2,
              "name": "reprehenderit",
              "label": "file-label",
              "balance": "$2,518.37",
              "highlight": "brown",
              "connection": {
                "_id": "619459088a15378404abf511",
                "index": 2,
                "label": "amet",
                "guid": "eaee15ac-d15a-4035-a91e-0827e165861f",
                "isActive": false,
                "balance": "$1,498.25",
                "picture": "http://placehold.it/32x32",
                "level": 25,
                "highlight": "blue",
                "about": "Et nisi cillum magna laborum eiusmod. Ea reprehenderit aute nisi ad anim amet labore aliqua exercitation. In ad duis sit qui esse pariatur anim et ad nisi nostrud ullamco.\r\n",
                "registered": "2016-05-21T02:00:06 +03:00",
                "latitude": -1.996668,
                "longitude": 143.94104,
                "tags": [
                  "ut",
                  "laboris",
                  "voluptate",
                  "nulla",
                  "culpa",
                  "non",
                  "cillum"
                ]
              }
            },
            {
              "id": 3,
              "name": "in",
              "label": "file-label",
              "balance": "$2,607.18",
              "highlight": "purple",
              "connection": {
                "_id": "61945908928aade5d4f39f17",
                "index": 3,
                "label": "laboris",
                "guid": "e11fbd29-26d7-4d64-b02a-a255b6611479",
                "isActive": false,
                "balance": "$3,728.91",
                "picture": "http://placehold.it/32x32",
                "level": 27,
                "highlight": "orange",
                "about": "Aute quis sint excepteur deserunt ut. Voluptate nisi nulla dolore cupidatat nisi duis cupidatat. Et deserunt excepteur sit tempor id ipsum. Est sint eiusmod exercitation adipisicing esse aute veniam minim adipisicing do aute. Lorem eiusmod eu nisi eiusmod aliqua elit ex ex.\r\n",
                "registered": "2018-04-21T04:47:17 +03:00",
                "latitude": 73.218567,
                "longitude": 7.894487,
                "tags": [
                  "consectetur",
                  "dolor",
                  "fugiat",
                  "deserunt",
                  "deserunt",
                  "id",
                  "irure"
                ]
              }
            }
          ]
        },
        {
          "id": 1,
          "name": "culpa",
          "label": "folder-label",
          "highlight": "green",
          "files": [
            {
              "id": 0,
              "name": "laborum",
              "label": "file-label",
              "balance": "$2,800.72",
              "highlight": "green",
              "connection": {
                "_id": "61945908115dc2018ca494a7",
                "index": 0,
                "label": "voluptate",
                "guid": "1a229c5e-ef66-4d71-a41a-f2611fb1a905",
                "isActive": true,
                "balance": "$1,176.78",
                "picture": "http://placehold.it/32x32",
                "level": 31,
                "highlight": "orange",
                "about": "In veniam laborum cillum ex velit non elit sunt ex in non laboris enim. Elit ut ad magna cillum incididunt commodo quis. Et do exercitation exercitation excepteur. Quis ipsum eu culpa id ipsum sunt ipsum consequat. Fugiat aliqua ut magna est et enim consequat aliquip fugiat.\r\n",
                "registered": "2015-09-13T10:58:57 +03:00",
                "latitude": -2.717975,
                "longitude": 77.195646,
                "tags": [
                  "velit",
                  "consectetur",
                  "officia",
                  "ipsum",
                  "nisi",
                  "Lorem",
                  "sint"
                ]
              }
            },
            {
              "id": 1,
              "name": "consectetur",
              "label": "file-label",
              "balance": "$2,102.05",
              "highlight": "yellow",
              "connection": {
                "_id": "61945908df0af4bd4a7ab88b",
                "index": 1,
                "label": "amet",
                "guid": "265c3e66-216b-4d37-a15f-90747b4342d0",
                "isActive": false,
                "balance": "$3,110.48",
                "picture": "http://placehold.it/32x32",
                "level": 31,
                "highlight": "yellow",
                "about": "Cillum adipisicing cupidatat nisi sint culpa exercitation ex cupidatat enim nostrud voluptate commodo non. Consectetur quis laborum sit sit occaecat tempor esse voluptate elit ipsum aute. Aliquip excepteur culpa adipisicing sunt consectetur laboris. Tempor aliquip aliquip culpa minim ipsum. Do voluptate reprehenderit magna dolor mollit deserunt pariatur ullamco. Et eu aliqua elit laborum mollit. Lorem officia Lorem qui aute elit veniam labore do cillum excepteur.\r\n",
                "registered": "2014-02-25T11:08:24 +03:00",
                "latitude": 53.22308,
                "longitude": -97.671776,
                "tags": [
                  "officia",
                  "enim",
                  "reprehenderit",
                  "deserunt",
                  "deserunt",
                  "nostrud",
                  "non"
                ]
              }
            }
          ]
        }
      ]
    },
    {
      "_id": "6194590836eff3460e579dea",
      "index": 2,
      "label": "ad",
      "guid": "a966b9a6-ed1b-4206-8500-91bae09e7cae",
      "isActive": false,
      "picture": "http://placehold.it/32x32",
      "level": 24,
      "about": "Eiusmod voluptate mollit in pariatur anim qui adipisicing. Officia minim ad eu enim enim ea sunt reprehenderit enim non Lorem. Qui aliqua sunt nisi ea do eu. Eiusmod cupidatat consectetur esse magna eu. Exercitation duis sunt nisi esse voluptate enim. Nostrud Lorem mollit aute exercitation qui cillum.\r\n",
      "registered": "2017-12-23T02:38:58 +02:00",
      "latitude": -48.181441,
      "longitude": 90.130826,
      "connections": [
        {
          "_id": "6194590898ebfe53111aa2f6",
          "index": 0,
          "label": "eiusmod",
          "guid": "a9d9dab6-644b-4336-905e-29042b6660b9",
          "isActive": true,
          "picture": "http://placehold.it/32x32",
          "level": 40,
          "about": "Magna duis ad aute non reprehenderit fugiat quis occaecat magna. Reprehenderit est labore incididunt cillum laboris adipisicing aute commodo incididunt sint dolore Lorem voluptate esse. Ut cillum dolor consectetur labore culpa ipsum exercitation.\r\n",
          "registered": "2016-09-06T11:14:34 +03:00",
          "latitude": 59.706875,
          "longitude": 58.716012,
          "tags": [
            "sit",
            "excepteur",
            "consequat",
            "culpa",
            "occaecat",
            "id",
            "duis"
          ]
        },
        {
          "_id": "61945908604113f3e460454d",
          "index": 1,
          "label": "labore",
          "guid": "d1999416-34b1-4813-96a6-0feda1fa6dc2",
          "isActive": true,
          "picture": "http://placehold.it/32x32",
          "level": 40,
          "about": "Incididunt labore commodo non Lorem eiusmod nulla laboris. Nulla esse veniam ex ipsum Lorem in. Excepteur nisi fugiat eu tempor deserunt ea. Quis minim laborum culpa dolore nulla fugiat quis qui id nostrud sit. Sunt duis ullamco aliquip elit cillum exercitation ipsum in laboris ea. Commodo id velit eiusmod quis reprehenderit occaecat tempor enim deserunt aliquip labore culpa.\r\n",
          "registered": "2017-08-03T07:40:28 +03:00",
          "latitude": 26.249282,
          "longitude": 110.128759,
          "tags": [
            "proident",
            "irure",
            "dolore",
            "quis",
            "nulla",
            "laborum",
            "tempor"
          ]
        },
        {
          "_id": "619459083072499a9e15c0e5",
          "index": 2,
          "label": "id",
          "guid": "28c9c121-a15b-4e20-9f6a-cedeede0e365",
          "isActive": true,
          "picture": "http://placehold.it/32x32",
          "level": 33,
          "about": "In sit id cupidatat eiusmod adipisicing aliquip eu deserunt esse. Mollit pariatur nulla officia non proident quis nulla ad aliquip incididunt do qui proident. Aliquip anim aute nulla officia adipisicing tempor. Enim reprehenderit consequat culpa laboris consectetur irure aliquip laboris culpa. Sit voluptate deserunt consectetur est officia eu non consequat eiusmod anim aliquip.\r\n",
          "registered": "2020-04-25T12:16:29 +03:00",
          "latitude": 58.150494,
          "longitude": 39.214299,
          "tags": [
            "exercitation",
            "qui",
            "velit",
            "in",
            "nulla",
            "ad",
            "mollit"
          ]
        },
        {
          "_id": "619459082b3120ee36002eb1",
          "index": 3,
          "label": "ullamco",
          "guid": "8b92f573-af19-408a-816e-72f6452268a9",
          "isActive": true,
          "picture": "http://placehold.it/32x32",
          "level": 22,
          "about": "Id nulla mollit Lorem est sit ex non duis culpa commodo cillum nulla laboris. Ut magna pariatur anim est. Aliqua proident ipsum officia incididunt laborum.\r\n",
          "registered": "2017-02-15T04:09:38 +02:00",
          "latitude": -85.323691,
          "longitude": -116.56284,
          "tags": [
            "adipisicing",
            "sunt",
            "nostrud",
            "veniam",
            "officia",
            "laborum",
            "est"
          ]
        }
      ],
      "tags": [
        "ea",
        "id",
        "dolor",
        "Lorem",
        "veniam",
        "nulla",
        "sit"
      ],
      "folders": [
        {
          "id": 0,
          "name": "et",
          "label": "folder-label",
          "highlight": "red",
          "files": [
            {
              "id": 0,
              "name": "dolore",
              "label": "file-label",
              "balance": "$2,679.89",
              "highlight": "green",
              "connection": {
                "_id": "61945908c0026f4a05dfa60c",
                "index": 0,
                "label": "enim",
                "guid": "284f15b6-1fcf-403a-917d-8afc62f338f5",
                "isActive": true,
                "balance": "$3,111.62",
                "picture": "http://placehold.it/32x32",
                "level": 40,
                "highlight": "purple",
                "about": "Ullamco irure est id laborum consectetur magna eiusmod labore in tempor. Sit qui in deserunt do dolor ullamco ipsum sint est anim. Tempor ad aute ullamco in magna officia. Incididunt velit tempor non duis dolor commodo ullamco mollit sint.\r\n",
                "registered": "2017-08-20T12:49:54 +03:00",
                "latitude": -78.756879,
                "longitude": 142.535042,
                "tags": [
                  "eiusmod",
                  "laboris",
                  "elit",
                  "enim",
                  "dolor",
                  "aliquip",
                  "do"
                ]
              }
            },
            {
              "id": 1,
              "name": "velit",
              "label": "file-label",
              "balance": "$2,423.38",
              "highlight": "purple",
              "connection": {
                "_id": "619459082b2187a0757bc3f1",
                "index": 1,
                "label": "consequat",
                "guid": "f50bcd19-d4eb-4b09-9074-a4932a1d9771",
                "isActive": false,
                "balance": "$1,522.34",
                "picture": "http://placehold.it/32x32",
                "level": 37,
                "highlight": "yellow",
                "about": "Excepteur nostrud velit ex elit sint sint sunt Lorem in sint minim commodo nostrud cupidatat. Aliquip velit anim amet ad esse irure exercitation nisi est nulla ad do officia. Esse ea deserunt enim anim tempor. Nisi excepteur commodo cupidatat eiusmod ut culpa anim consequat. Eu id dolore eu officia laborum dolore nostrud aliqua sunt dolor ullamco. Sit incididunt ut minim irure officia excepteur sint ex excepteur. Proident et in sint nostrud cupidatat officia aute exercitation non.\r\n",
                "registered": "2016-07-06T03:07:35 +03:00",
                "latitude": -27.682364,
                "longitude": 43.640234,
                "tags": [
                  "nisi",
                  "anim",
                  "in",
                  "occaecat",
                  "cupidatat",
                  "nulla",
                  "duis"
                ]
              }
            }
          ]
        }
      ]
    }
  ]
}